.gitignore
LICENSE
MANIFEST.in
Makefile
README.md
lock-acquire.py
lock-get.py
lock-list-locks.py
lock-list-resources.py
lock-release.py
setup.py
rdlm_py.egg-info/PKG-INFO
rdlm_py.egg-info/SOURCES.txt
rdlm_py.egg-info/dependency_links.txt
rdlm_py.egg-info/requires.txt
rdlm_py.egg-info/top_level.txt
rdlmpy/__init__.py
rdlmpy/__init__.pyc
rdlmpy/client.py
rdlmpy/client.pyc
rdlmpy/context.py
rdlmpy/context.pyc
rdlmpy/exceptions.py
rdlmpy/exceptions.pyc
rdlmpy/lock.py
rdlmpy/lock.pyc
tests/.coverage
tests/lock1.json
tests/test_client.py
tests/test_client.pyc
tests/test_context.py
tests/test_context.pyc
tests/htmlcov/_Users_fab_Documents_rdlm-py_rdlmpy___init__.html
tests/htmlcov/_Users_fab_Documents_rdlm-py_rdlmpy_client.html
tests/htmlcov/_Users_fab_Documents_rdlm-py_rdlmpy_context.html
tests/htmlcov/_Users_fab_Documents_rdlm-py_rdlmpy_exceptions.html
tests/htmlcov/_Users_fab_Documents_rdlm-py_rdlmpy_lock.html
tests/htmlcov/coverage_html.js
tests/htmlcov/index.html
tests/htmlcov/jquery-1.4.3.min.js
tests/htmlcov/jquery.hotkeys.js
tests/htmlcov/jquery.isonscreen.js
tests/htmlcov/jquery.tablesorter.min.js
tests/htmlcov/keybd_closed.png
tests/htmlcov/keybd_open.png
tests/htmlcov/status.dat
tests/htmlcov/style.css