Metadata-Version: 1.1
Name: rdlm-py
Version: 0.2.0
Summary: rdlm-py is a python client for RDLM (Restful Distributed Lock Manager)
Home-page: https://github.com/thefab/rdlm-py
Author: Fabien MARTY
Author-email: fabien.marty@gmail.com
License: MIT
Download-URL: https://github.com/thefab/rdlm-py
Platform: UNKNOWN
Classifier: Development Status :: 4 - Beta
Classifier: Environment :: Console
Classifier: Intended Audience :: Developers
Classifier: Intended Audience :: Developers
Classifier: Intended Audience :: System Administrators
Classifier: Intended Audience :: System Administrators
Classifier: License :: OSI Approved :: MIT License
Classifier: Operating System :: MacOS :: MacOS X
Classifier: Operating System :: POSIX
Classifier: Operating System :: Unix
Classifier: Programming Language :: Python :: 2.6
Classifier: Programming Language :: Python :: 2.7
Classifier: Programming Language :: Python :: 3.2
Classifier: Programming Language :: Python :: 3.3
Classifier: Topic :: Utilities
Classifier: Topic :: System :: Distributed Computing
Classifier: Topic :: Software Development
